{
  "failed": [],
  "generated_utc": "2026-05-15T00:15:15Z",
  "prices": {
    "ABBV": {
      "asof_utc": "2026-05-14T04:00:00Z",
      "change_pct": 1.0887310659285054,
      "currency": "USD",
      "price": 210.77000427246094,
      "source": "yfinance"
    },
    "AMZN": {
      "asof_utc": "2026-05-14T04:00:00Z",
      "change_pct": -1.0772604336833247,
      "currency": "USD",
      "price": 267.2200012207031,
      "source": "yfinance"
    },
    "AVGO": {
      "asof_utc": "2026-05-14T04:00:00Z",
      "change_pct": 5.5183664503610785,
      "currency": "USD",
      "price": 439.7900085449219,
      "source": "yfinance"
    },
    "COST": {
      "asof_utc": "2026-05-14T04:00:00Z",
      "change_pct": 0.7908433318669417,
      "currency": "USD",
      "price": 1041.25,
      "source": "yfinance"
    },
    "CRWD": {
      "asof_utc": "2026-05-14T04:00:00Z",
      "change_pct": 3.089394147668467,
      "currency": "USD",
      "price": 579.9500122070312,
      "source": "yfinance"
    },
    "DASH": {
      "asof_utc": "2026-05-14T04:00:00Z",
      "change_pct": 3.1059162786203354,
      "currency": "USD",
      "price": 153.6999969482422,
      "source": "yfinance"
    },
    "EOG": {
      "asof_utc": "2026-05-14T04:00:00Z",
      "change_pct": 0.7856020713866707,
      "currency": "USD",
      "price": 135.99000549316406,
      "source": "yfinance"
    },
    "GOOGL": {
      "asof_utc": "2026-05-14T04:00:00Z",
      "change_pct": -0.3849753643053955,
      "currency": "USD",
      "price": 401.07000732421875,
      "source": "yfinance"
    },
    "INTC": {
      "asof_utc": "2026-05-14T04:00:00Z",
      "change_pct": -3.6245744261098944,
      "currency": "USD",
      "price": 115.93000030517578,
      "source": "yfinance"
    },
    "JPM": {
      "asof_utc": "2026-05-14T04:00:00Z",
      "change_pct": -0.11323774784034457,
      "currency": "USD",
      "price": 299.9100036621094,
      "source": "yfinance"
    },
    "LLY": {
      "asof_utc": "2026-05-14T04:00:00Z",
      "change_pct": -0.8909660637921535,
      "currency": "USD",
      "price": 1006.7000122070312,
      "source": "yfinance"
    },
    "META": {
      "asof_utc": "2026-05-14T04:00:00Z",
      "change_pct": 0.29190726671026734,
      "currency": "USD",
      "price": 618.4299926757812,
      "source": "yfinance"
    },
    "MSFT": {
      "asof_utc": "2026-05-14T04:00:00Z",
      "change_pct": 1.041435628363807,
      "currency": "USD",
      "price": 409.42999267578125,
      "source": "yfinance"
    },
    "MU": {
      "asof_utc": "2026-05-14T04:00:00Z",
      "change_pct": -3.436904414888675,
      "currency": "USD",
      "price": 776.010009765625,
      "source": "yfinance"
    },
    "NEE": {
      "asof_utc": "2026-05-14T04:00:00Z",
      "change_pct": 0.8750678380676558,
      "currency": "USD",
      "price": 95.68000030517578,
      "source": "yfinance"
    },
    "NFLX": {
      "asof_utc": "2026-05-14T04:00:00Z",
      "change_pct": -0.708080327175209,
      "currency": "USD",
      "price": 86.94000244140625,
      "source": "yfinance"
    },
    "NVDA": {
      "asof_utc": "2026-05-14T04:00:00Z",
      "change_pct": 4.388258239276421,
      "currency": "USD",
      "price": 235.74000549316406,
      "source": "yfinance"
    },
    "ORCL": {
      "asof_utc": "2026-05-14T04:00:00Z",
      "change_pct": 3.082844789661343,
      "currency": "USD",
      "price": 195.61000061035156,
      "source": "yfinance"
    },
    "PANW": {
      "asof_utc": "2026-05-14T04:00:00Z",
      "change_pct": 4.574394720950514,
      "currency": "USD",
      "price": 238.2100067138672,
      "source": "yfinance"
    },
    "PLTR": {
      "asof_utc": "2026-05-14T04:00:00Z",
      "change_pct": 2.829675193715042,
      "currency": "USD",
      "price": 133.72999572753906,
      "source": "yfinance"
    },
    "QQQ": {
      "asof_utc": "2026-05-14T04:00:00Z",
      "change_pct": 0.7107716274449949,
      "currency": "USD",
      "price": 719.7899780273438,
      "source": "yfinance"
    },
    "SCHD": {
      "asof_utc": "2026-05-14T04:00:00Z",
      "change_pct": 0.15747791200171335,
      "currency": "USD",
      "price": 31.799999237060547,
      "source": "yfinance"
    },
    "TSM": {
      "asof_utc": "2026-05-14T04:00:00Z",
      "change_pct": 4.482244616028863,
      "currency": "USD",
      "price": 417.7200012207031,
      "source": "yfinance"
    },
    "UNH": {
      "asof_utc": "2026-05-14T04:00:00Z",
      "change_pct": -0.5160054106396639,
      "currency": "USD",
      "price": 399.0899963378906,
      "source": "yfinance"
    },
    "V": {
      "asof_utc": "2026-05-14T04:00:00Z",
      "change_pct": 0.6899539420944345,
      "currency": "USD",
      "price": 322.5199890136719,
      "source": "yfinance"
    },
    "VUG": {
      "asof_utc": "2026-05-14T04:00:00Z",
      "change_pct": 1.1198671050349995,
      "currency": "USD",
      "price": 88.48999786376953,
      "source": "yfinance"
    },
    "XOM": {
      "asof_utc": "2026-05-14T04:00:00Z",
      "change_pct": 0.7983053352302649,
      "currency": "USD",
      "price": 152.77999877929688,
      "source": "yfinance"
    },
    "^GSPC": {
      "asof_utc": "2026-05-14T04:00:00Z",
      "change_pct": 0.7655604577358366,
      "currency": "USD",
      "price": 7501.240234375,
      "source": "yfinance"
    },
    "^IXIC": {
      "asof_utc": "2026-05-14T04:00:00Z",
      "change_pct": 0.8820536887192976,
      "currency": "USD",
      "price": 26635.22265625,
      "source": "yfinance"
    },
    "^NDX": {
      "asof_utc": "2026-05-14T04:00:00Z",
      "change_pct": 0.7265291479916058,
      "currency": "USD",
      "price": 29580.298828125,
      "source": "yfinance"
    }
  },
  "ticker_count": 30
}
