{
  "failed": [],
  "generated_utc": "2026-06-25T15:34:38Z",
  "prices": {
    "ABBV": {
      "asof_utc": "2026-06-25T04:00:00Z",
      "change_pct": 3.192983958230844,
      "currency": "USD",
      "price": 242.38999938964844,
      "source": "yfinance"
    },
    "AMZN": {
      "asof_utc": "2026-06-25T04:00:00Z",
      "change_pct": -1.5836456422958722,
      "currency": "USD",
      "price": 230.55999755859375,
      "source": "yfinance"
    },
    "AVGO": {
      "asof_utc": "2026-06-25T04:00:00Z",
      "change_pct": -0.21069245435383355,
      "currency": "USD",
      "price": 381.2650146484375,
      "source": "yfinance"
    },
    "COST": {
      "asof_utc": "2026-06-25T04:00:00Z",
      "change_pct": -1.3183057389455244,
      "currency": "USD",
      "price": 948.419921875,
      "source": "yfinance"
    },
    "CRWD": {
      "asof_utc": "2026-06-25T04:00:00Z",
      "change_pct": 1.2941607507554354,
      "currency": "USD",
      "price": 681.72998046875,
      "source": "yfinance"
    },
    "DASH": {
      "asof_utc": "2026-06-25T04:00:00Z",
      "change_pct": -0.578878672340366,
      "currency": "USD",
      "price": 176.89999389648438,
      "source": "yfinance"
    },
    "EOG": {
      "asof_utc": "2026-06-25T04:00:00Z",
      "change_pct": -0.490891541160432,
      "currency": "USD",
      "price": 133.7899932861328,
      "source": "yfinance"
    },
    "GOOGL": {
      "asof_utc": "2026-06-25T04:00:00Z",
      "change_pct": -1.1063185234685857,
      "currency": "USD",
      "price": 341.4700012207031,
      "source": "yfinance"
    },
    "INTC": {
      "asof_utc": "2026-06-25T04:00:00Z",
      "change_pct": -1.5267714394399334,
      "currency": "USD",
      "price": 129.63999938964844,
      "source": "yfinance"
    },
    "JPM": {
      "asof_utc": "2026-06-25T04:00:00Z",
      "change_pct": 2.147240330609379,
      "currency": "USD",
      "price": 340.6099853515625,
      "source": "yfinance"
    },
    "LLY": {
      "asof_utc": "2026-06-25T04:00:00Z",
      "change_pct": 1.8187302965694707,
      "currency": "USD",
      "price": 1137.5799560546875,
      "source": "yfinance"
    },
    "META": {
      "asof_utc": "2026-06-25T04:00:00Z",
      "change_pct": -0.5962329529877075,
      "currency": "USD",
      "price": 554.344970703125,
      "source": "yfinance"
    },
    "MSFT": {
      "asof_utc": "2026-06-25T04:00:00Z",
      "change_pct": -2.588491250349778,
      "currency": "USD",
      "price": 356.0000915527344,
      "source": "yfinance"
    },
    "MU": {
      "asof_utc": "2026-06-25T04:00:00Z",
      "change_pct": 12.246905893477479,
      "currency": "USD",
      "price": 1176.9200439453125,
      "source": "yfinance"
    },
    "NEE": {
      "asof_utc": "2026-06-25T04:00:00Z",
      "change_pct": -0.6642327256085157,
      "currency": "USD",
      "price": 87.03800201416016,
      "source": "yfinance"
    },
    "NFLX": {
      "asof_utc": "2026-06-25T04:00:00Z",
      "change_pct": 0.7307928071288217,
      "currency": "USD",
      "price": 72.36499786376953,
      "source": "yfinance"
    },
    "NVDA": {
      "asof_utc": "2026-06-25T04:00:00Z",
      "change_pct": -1.7487415716276655,
      "currency": "USD",
      "price": 195.52000427246094,
      "source": "yfinance"
    },
    "ORCL": {
      "asof_utc": "2026-06-25T04:00:00Z",
      "change_pct": -3.319999852768618,
      "currency": "USD",
      "price": 152.3000030517578,
      "source": "yfinance"
    },
    "PANW": {
      "asof_utc": "2026-06-25T04:00:00Z",
      "change_pct": 2.9131309241072323,
      "currency": "USD",
      "price": 293.57000732421875,
      "source": "yfinance"
    },
    "PLTR": {
      "asof_utc": "2026-06-25T04:00:00Z",
      "change_pct": -5.356829807096641,
      "currency": "USD",
      "price": 107.41999816894531,
      "source": "yfinance"
    },
    "QQQ": {
      "asof_utc": "2026-06-25T04:00:00Z",
      "change_pct": 0.47001588449786524,
      "currency": "USD",
      "price": 713.9600219726562,
      "source": "yfinance"
    },
    "SCHD": {
      "asof_utc": "2026-06-25T04:00:00Z",
      "change_pct": 1.1506928720660392,
      "currency": "USD",
      "price": 32.084999084472656,
      "source": "yfinance"
    },
    "TSM": {
      "asof_utc": "2026-06-25T04:00:00Z",
      "change_pct": -0.041965738318350265,
      "currency": "USD",
      "price": 440.6449890136719,
      "source": "yfinance"
    },
    "UNH": {
      "asof_utc": "2026-06-25T04:00:00Z",
      "change_pct": 2.171019670677876,
      "currency": "USD",
      "price": 414.6099853515625,
      "source": "yfinance"
    },
    "V": {
      "asof_utc": "2026-06-25T04:00:00Z",
      "change_pct": 1.4417656048359984,
      "currency": "USD",
      "price": 337.0199890136719,
      "source": "yfinance"
    },
    "VUG": {
      "asof_utc": "2026-06-25T04:00:00Z",
      "change_pct": -0.8170086621793748,
      "currency": "USD",
      "price": 83.14510345458984,
      "source": "yfinance"
    },
    "XOM": {
      "asof_utc": "2026-06-25T04:00:00Z",
      "change_pct": 0.5843704071767375,
      "currency": "USD",
      "price": 137.6999969482422,
      "source": "yfinance"
    },
    "^GSPC": {
      "asof_utc": "2026-06-25T04:00:00Z",
      "change_pct": 0.21037669459147423,
      "currency": "USD",
      "price": 7373.7001953125,
      "source": "yfinance"
    },
    "^IXIC": {
      "asof_utc": "2026-06-25T04:00:00Z",
      "change_pct": -0.40232933968310514,
      "currency": "USD",
      "price": 25374.140625,
      "source": "yfinance"
    },
    "^NDX": {
      "asof_utc": "2026-06-25T04:00:00Z",
      "change_pct": 0.41526212293552245,
      "currency": "USD",
      "price": 29341.400390625,
      "source": "yfinance"
    }
  },
  "ticker_count": 30
}
