{
  "failed": [],
  "generated_utc": "2026-06-29T16:40:44Z",
  "prices": {
    "ABBV": {
      "asof_utc": "2026-06-29T04:00:00Z",
      "change_pct": 0.268400497098642,
      "currency": "USD",
      "price": 254.02999877929688,
      "source": "yfinance"
    },
    "AMZN": {
      "asof_utc": "2026-06-29T04:00:00Z",
      "change_pct": 3.0920933387507565,
      "currency": "USD",
      "price": 239.88499450683594,
      "source": "yfinance"
    },
    "AVGO": {
      "asof_utc": "2026-06-29T04:00:00Z",
      "change_pct": 1.4821116171549464,
      "currency": "USD",
      "price": 370.42999267578125,
      "source": "yfinance"
    },
    "COST": {
      "asof_utc": "2026-06-29T04:00:00Z",
      "change_pct": -0.5280584938949784,
      "currency": "USD",
      "price": 947.510009765625,
      "source": "yfinance"
    },
    "CRWD": {
      "asof_utc": "2026-06-29T04:00:00Z",
      "change_pct": 6.88500459533099,
      "currency": "USD",
      "price": 749.360107421875,
      "source": "yfinance"
    },
    "DASH": {
      "asof_utc": "2026-06-29T04:00:00Z",
      "change_pct": 0.20755087138195627,
      "currency": "USD",
      "price": 183.47000122070312,
      "source": "yfinance"
    },
    "EOG": {
      "asof_utc": "2026-06-29T04:00:00Z",
      "change_pct": 0.5090405444188484,
      "currency": "USD",
      "price": 133.27499389648438,
      "source": "yfinance"
    },
    "GOOGL": {
      "asof_utc": "2026-06-29T04:00:00Z",
      "change_pct": 3.9983371317114047,
      "currency": "USD",
      "price": 350.8800048828125,
      "source": "yfinance"
    },
    "INTC": {
      "asof_utc": "2026-06-29T04:00:00Z",
      "change_pct": -0.3351059149208413,
      "currency": "USD",
      "price": 127.88999938964844,
      "source": "yfinance"
    },
    "JPM": {
      "asof_utc": "2026-06-29T04:00:00Z",
      "change_pct": 0.9481919922539772,
      "currency": "USD",
      "price": 332.1700134277344,
      "source": "yfinance"
    },
    "LLY": {
      "asof_utc": "2026-06-29T04:00:00Z",
      "change_pct": 0.7275698629038096,
      "currency": "USD",
      "price": 1216.909912109375,
      "source": "yfinance"
    },
    "META": {
      "asof_utc": "2026-06-29T04:00:00Z",
      "change_pct": 2.413453756815076,
      "currency": "USD",
      "price": 563.530029296875,
      "source": "yfinance"
    },
    "MSFT": {
      "asof_utc": "2026-06-29T04:00:00Z",
      "change_pct": -1.3111013305179609,
      "currency": "USD",
      "price": 368.0799865722656,
      "source": "yfinance"
    },
    "MU": {
      "asof_utc": "2026-06-29T04:00:00Z",
      "change_pct": -1.586106668066689,
      "currency": "USD",
      "price": 1114.3699951171875,
      "source": "yfinance"
    },
    "NEE": {
      "asof_utc": "2026-06-29T04:00:00Z",
      "change_pct": -0.5871687640035872,
      "currency": "USD",
      "price": 88.04000091552734,
      "source": "yfinance"
    },
    "NFLX": {
      "asof_utc": "2026-06-29T04:00:00Z",
      "change_pct": 1.1926601521702995,
      "currency": "USD",
      "price": 74.69029998779297,
      "source": "yfinance"
    },
    "NVDA": {
      "asof_utc": "2026-06-29T04:00:00Z",
      "change_pct": 0.20750304771588457,
      "currency": "USD",
      "price": 192.92950439453125,
      "source": "yfinance"
    },
    "ORCL": {
      "asof_utc": "2026-06-29T04:00:00Z",
      "change_pct": -0.5184166692178471,
      "currency": "USD",
      "price": 147.75999450683594,
      "source": "yfinance"
    },
    "PANW": {
      "asof_utc": "2026-06-29T04:00:00Z",
      "change_pct": 8.99078714281043,
      "currency": "USD",
      "price": 331.54998779296875,
      "source": "yfinance"
    },
    "PLTR": {
      "asof_utc": "2026-06-29T04:00:00Z",
      "change_pct": 2.311166743379478,
      "currency": "USD",
      "price": 115.54000091552734,
      "source": "yfinance"
    },
    "QQQ": {
      "asof_utc": "2026-06-29T04:00:00Z",
      "change_pct": 1.889539604949153,
      "currency": "USD",
      "price": 719.8699951171875,
      "source": "yfinance"
    },
    "SCHD": {
      "asof_utc": "2026-06-29T04:00:00Z",
      "change_pct": -0.5141817224766698,
      "currency": "USD",
      "price": 31.924999237060547,
      "source": "yfinance"
    },
    "TSM": {
      "asof_utc": "2026-06-29T04:00:00Z",
      "change_pct": 4.18295159009392,
      "currency": "USD",
      "price": 450.43499755859375,
      "source": "yfinance"
    },
    "UNH": {
      "asof_utc": "2026-06-29T04:00:00Z",
      "change_pct": -1.9514374763748954,
      "currency": "USD",
      "price": 419.5400085449219,
      "source": "yfinance"
    },
    "V": {
      "asof_utc": "2026-06-29T04:00:00Z",
      "change_pct": 1.4513797715198118,
      "currency": "USD",
      "price": 341.1099853515625,
      "source": "yfinance"
    },
    "VUG": {
      "asof_utc": "2026-06-29T04:00:00Z",
      "change_pct": 1.999876653822863,
      "currency": "USD",
      "price": 84.41510009765625,
      "source": "yfinance"
    },
    "XOM": {
      "asof_utc": "2026-06-29T04:00:00Z",
      "change_pct": -0.0878827618923661,
      "currency": "USD",
      "price": 136.4199981689453,
      "source": "yfinance"
    },
    "^GSPC": {
      "asof_utc": "2026-06-29T04:00:00Z",
      "change_pct": 0.797388864362758,
      "currency": "USD",
      "price": 7412.66015625,
      "source": "yfinance"
    },
    "^IXIC": {
      "asof_utc": "2026-06-29T04:00:00Z",
      "change_pct": 1.333723892155425,
      "currency": "USD",
      "price": 25635.01953125,
      "source": "yfinance"
    },
    "^NDX": {
      "asof_utc": "2026-06-29T04:00:00Z",
      "change_pct": 1.652053229360706,
      "currency": "USD",
      "price": 29599.2890625,
      "source": "yfinance"
    }
  },
  "ticker_count": 30
}
